{"P1":{ "proyecto":"P1","organismo":"SG Política forestal","contactos":[{"nombre": "Antonio Pérez", "email": "aperez@mapa.es", "telefono":"912345678", "movil":"654321098"},{"nombre": "Juanita Banana", "email": "jbanana@mapa.es","telefono":"912345678", "movil":"654321098"}],"ficherofuentes":"P1Sources.csv","diccionariodatos":"P1DataDict.csv","descripcion":"Clasificación del riesgo de incendios por provincias y municipios en función de variables socioeconómicas"},"F32":{"proyecto":"F32","organismo":"SG Cultivos frutícolas","contactos":[{"nombre": "María González", "email": "mgonzalez@mapa.es", "telefono":"912345678", "movil":"654321098"},{"nombre": "Pepito Gómez", "email": "pgomez@mapa.es", "telefono":"912345678", "movil":"654321098"}],"ficherofuentes":"F32Sources.csv","diccionariodatos":"F32DataDict.csv","descripcion":"Proyecto en pruebas. Sin descripción"}}